sluggable/__init__.py
sluggable/fields.py
sluggable/models.py
sluggable/settings.py
sluggable/utils.py
sluggable/views.py
sluggable/tests/__init__.py
sluggable/tests/models.py
sluggable/tests/settings.py
sluggable/tests/tests.py
sluggable/tests/migrations/0001_initial.py
sluggable/tests/migrations/__init__.py
mysociety_django_sluggable-0.6.1.1.dist-info/METADATA
mysociety_django_sluggable-0.6.1.1.dist-info/WHEEL
mysociety_django_sluggable-0.6.1.1.dist-info/top_level.txt
mysociety_django_sluggable-0.6.1.1.dist-info/RECORD
