Metadata-Version: 2.1
Name: mysociety-django-sluggable
Version: 0.6.1.1
Summary: Slug your multiple models and manage redirections
Home-page: http://github.com/mysociety/django-sluggable
Author: Florent Messa
Author-email: florent.messa@gmail.com
Maintainer: Matthew Somerville
Maintainer-email: matthew@mysociety.org
License: UNKNOWN
Platform: UNKNOWN
Classifier: Environment :: Web Environment
Classifier: Intended Audience :: Developers
Classifier: License :: OSI Approved :: MIT License
Classifier: Operating System :: OS Independent
Classifier: Programming Language :: Python
Classifier: Programming Language :: Python :: 3
Classifier: Topic :: Utilities
